Workbook
Name _1_2007_InternetDataFile_ExistGenUnits: #REF!
Name AnswerData: #REF!
Name bprint: #REF!
Name cprint: #REF!
Name exch_rate: #REF!
Name fitfile: [1]MODEL!$D$38
Name INF: [1]MODEL!$H$14
Name PPP: [1]MODEL!$D$12
Name PPPEX: [1]MODEL!$D$13
Name rail_coal: #REF!

Sheet ANSv6.0-Technologies
A1: ANSWER-Technologies
B7: TechName | C7: TechDesc | D7: TACTUnit | E7: TCAPUnit | F7: Set Memberships | G7: Comment

Sheet ANSv6.0-Commodities
A1: ANSWER-Commodities
B7: CommName | C7: CommDesc | D7: CommUnit | E7: Set Memberships | F7: Comment

Sheet ANSv6.1-Commodities
A1: ANSWER-Commodities
B7: CommName | C7: CommDesc | D7: CommUnit | E7: Set Memberships | F7: Comment

Sheet ANSv6.1-Technologies
A1: ANSWER-Technologies
B7: TechName | C7: TechDesc | D7: TACTUnit | E7: TCAPUnit | F7: Set Memberships | G7: Comment

Sheet ANSv6.1-Constraints
A1: ANSWER-Constraints
B7: ConstrName | C7: ConstrDesc | D7: Units | E7: Set Memberships | F7: Comment

Sheet ANSv6.1-CommData
A1: ANSWER-CommData
B7: CommName | C7: CommDesc | D7: Units

Sheet ANSv6.1-TechData
A1: ANSWER-TechData
B7: TechName | C7: TechDesc | D7: Units | E7: CommIN | F7: CommOUT

Sheet ANSv6.1-ConstrData
A1: ANSWER-ConstrData
B7: ConstrName | C7: ConstrDesc | D7: Units | E7: TechName

Sheet Constraints
A1: UC - All Regions/Each Period
B2: ~UC_Sets: R_S: AllRegions
G4: ~UC_T
B5: UC_N | C5: Pset_PN | D5: Pset_Set | E5: Cset_CN | F5: Year | G5: LimType | H5: UC_COMPRD | I5: UC_RHSTS | J5: UC_RHSTS~0 | K5: UC_Desc
B6: BDL_AllRegions | E6: TRBDL1 | F6: 2010 | G6: FX | H6: 1 | I6: ='orig const'!M15 -> 42.151174 | K6: Biodiesel bounds on total production
B7: ETH_IMP_AllRegions | E7: ETHIMP | F7: 2010 | G7: FX | H7: 1 | I7: ='orig const'!M18 -> 15.985305 | K7: Ethanol bounds on total imports
B8: ETH_IMP_AllRegions | E8: ETHIMP | F8: 2011 | G8: FX | H8: 1 | I8: =I7+(I9-I7)/5 -> 33.076104 | J8: 5 | K8: Ethanol bounds on total imports
B9: ETH_IMP_AllRegions | E9: ETHIMP | F9: 2015 | G9: FX | H9: 1 | I9: ='orig const'!N18 -> 101.4393 | J9: 5 | K9: Ethanol bounds on total imports
B10: ETH_IMP_AllRegions | E10: ETHIMP | F10: 2020 | G10: FX | H10: 1 | I10: ='orig const'!O18 -> 269.28673 | J10: 5 | K10: Ethanol bounds on total imports
B11: ETH_IMP_AllRegions | E11: ETHIMP | F11: 2025 | G11: FX | H11: 1 | I11: ='orig const'!P18 -> 314.16785 | J11: 5 | K11: Ethanol bounds on total imports
B12: ETH_EXP_AllRegions | E12: ETHEXP | F12: 2010 | G12: FX | H12: 1 | I12: ='orig const'!M20 -> 25.313215 | K12: Ethanol bounds on total exports
B13: ETH_EXP_AllRegions | E13: ETHEXP | F13: 2011 | G13: FX | H13: 1 | I13: =I12+(I14-I12)/5 -> 22.918825 | J13: 5 | K13: Ethanol bounds on total exports
B14: ETH_EXP_AllRegions | E14: ETHEXP | F14: 2015 | G14: FX | H14: 1 | I14: ='orig const'!N20 -> 13.341267 | J14: 5 | K14: Ethanol bounds on total exports
B15: ETH_EXP_AllRegions | E15: ETHEXP | F15: 2020 | G15: FX | H15: 1 | I15: ='orig const'!O20 -> 14.483977 | J15: 5 | K15: Ethanol bounds on total exports
B16: ETH_EXP_AllRegions | E16: ETHEXP | F16: 2025 | G16: FX | H16: 1 | I16: ='orig const'!P20 -> 14.376036 | J16: 5 | K16: Ethanol bounds on total exports
B17: BDL_IMP_AllRegions | E17: BDLIMP | F17: 2010 | G17: FX | H17: 1 | I17: ='orig const'!M23 -> 0 | K17: Biodiesel bounds on total imports
B18: BDL_IMP_AllRegions | E18: BDLIMP | F18: 2011 | G18: FX | H18: 1 | I18: =I17+(I19-I17)/5 -> 2.348957 | J18: 5 | K18: Biodiesel bounds on total imports
B19: BDL_IMP_AllRegions | E19: BDLIMP | F19: 2015 | G19: FX | H19: 1 | I19: ='orig const'!N23 -> 11.744785 | J19: 5 | K19: Biodiesel bounds on total imports
B20: BDL_IMP_AllRegions | E20: BDLIMP | F20: 2020 | G20: FX | H20: 1 | I20: ='orig const'!O23 -> 3.9459885 | J20: 5 | K20: Biodiesel bounds on total imports
B21: BDL_IMP_AllRegions | E21: BDLIMP | F21: 2025 | G21: FX | H21: 1 | I21: ='orig const'!P23 -> 0 | J21: 5 | K21: Biodiesel bounds on total imports
B22: BDL_EXP_AllRegions | C22: XBDLEXP | E22: BDLEXP | F22: 2010 | G22: FX | H22: 1 | I22: ='orig const'!M25 -> 9.4642116 | K22: Biodiesel bounds on total exports
B23: BDL_EXP_AllRegions | C23: XBDLEXP | E23: BDLEXP | F23: 2011 | G23: FX | H23: 1 | I23: =I22+(I24-I22)/5 -> 7.5713693 | J23: 5 | K23: Biodiesel bounds on total exports
B24: BDL_EXP_AllRegions | C24: XBDLEXP | E24: BDLEXP | F24: 2015 | G24: FX | H24: 1 | I24: ='orig const'!N25 -> 0 | J24: 5 | K24: Biodiesel bounds on total exports
B25: BDL_EXP_AllRegions | C25: XBDLEXP | E25: BDLEXP | F25: 2020 | G25: FX | H25: 1 | I25: ='orig const'!O25 -> 0 | J25: 5 | K25: Biodiesel bounds on total exports
B26: BDL_EXP_AllRegions | C26: XBDLEXP | E26: BDLEXP | F26: 2025 | G26: FX | H26: 1 | I26: ='orig const'!P25 -> 1.503658 | J26: 5 | K26: Biodiesel bounds on total exports
B27: ETH_CRN_2010 | C27: XCRNETH | E27: ETH | F27: 2010 | G27: FX | H27: 1 | I27: ='orig const'!M10 -> 1187.6224 | K27: XCRNETH bounds_2010
B28: ETH_CRN_AllRegions | C28: XCRNETH | E28: ETH | F28: 2011 | G28: LO | H28: 1 | I28: =I27+(I29-I27)/5 -> 1219.3846 | J28: 5 | K28: XCRNETH bounds
B29: ETH_CRN_AllRegions | C29: XCRNETH | E29: ETH | F29: 2015 | G29: LO | H29: 1 | I29: ='orig const'!Q12 -> 1346.4337 | J29: 5 | K29: XCRNETH bounds
B30: ETH_CRN_AllRegions | C30: XCRNETH | E30: ETH | F30: 2020 | G30: LO | H30: 1 | I30: ='orig const'!R12 -> 1346.4337 | J30: 5 | K30: XCRNETH bounds
B31: ETH_CRN_AllRegions | C31: XCRNETH | E31: ETH | F31: 2055 | G31: LO | H31: 1 | I31: ='orig const'!S12 -> 1346.4337 | J31: 5 | K31: XCRNETH bounds
B32: E85_AllRegions | C32: XBLNDE85 | E32: TRNE85 | F32: 2010 | G32: FX | H32: 1 | I32: ='orig const'!M31 -> 12.054576 | K32: E85 total production
B33: E85_AllRegions | C33: XBLNDE85 | E33: TRNE85 | F33: 2011 | G33: FX | H33: 1 | I33: =I32+(I34-I32)/5 -> 14.465491 | K33: E85 total production
B34: E85_AllRegions | C34: XBLNDE85 | E34: TRNE85 | F34: 2015 | G34: FX | H34: 1 | I34: ='orig const'!N31 -> 24.109151 | J34: 5 | K34: E85 total production
B35: E85_AllRegions | C35: XBLNDE85 | E35: TRNE85 | F35: 2050 | G35: FX | H35: 1 | I35: =I34*1.1 -> 26.520066 | J35: 5 | K35: E85 total production
B36: *E10_AllRegions | C36: XBLNDE10 | E36: TRNE10 | F36: 2010 | G36: UP | H36: 1 | I36: 300 | J36: 5 | K36: E10 total production
B37: *E10_AllRegions | C37: XBLNDE10 | E37: TRNE10 | F37: 2050 | G37: UP | H37: 1 | I37: =I36*1.1 -> 330 | J37: 5 | K37: E10 total production
B38: B20_AllRegions | C38: XBLNDB20 | E38: TRNB20 | F38: 2010 | G38: UP | H38: 1 | I38: 150 | J38: 5 | K38: B20 total production
B39: B20_AllRegions | C39: XBLNDB20 | E39: TRNB20 | F39: 2050 | G39: UP | H39: 1 | I39: 150 | J39: 5 | K39: B20 total production

Sheet orig const
A1: *
A2: ConstrData | B2: _GLOBAL,R1,R2,R3,R4,R5,R6,R7,R8,R9 | T2: * | U2: * | V2: * | W2: * | X2: * | Y2: * | Z2: * | AA2: *
F6: RAT_ACT | G6: RATRULE_ACT | H6: RATRULE_CAP | I6: RAT__RHS | J6: RAT__XRRHS | K6: RAT__XRRHS | L6: RAT__XRRHS | M6: RAT__XRRHS | N6: RAT__XRRHS | O6: RAT__XRRHS | P6: RAT__XRRHS | Q6: RAT__XRRHS | R6: RAT__XRRHS | S6: RAT__XRRHS | T6: RAT__XRRHS | U6: RAT__XRRHS | V6: RAT__XRRHS | W6: RAT__XRRHS | X6: RAT__XRRHS | Y6: RAT__XRRHS | Z6: RAT__XRRHS | AA6: RAT__XRRHS
I7: UP | J7: UP | K7: UP | L7: UP | M7: FX | N7: FX | O7: FX | P7: FX | Q7: LO | R7: LO | S7: LO | T7: NON | U7: NON | V7: NON | W7: NON | X7: NON | Y7: NON | Z7: NON | AA7: NON
B8: ConstrName | C8: ConstrDesc | D8: Units | E8: TechName | F8: 2005-2055 | G8: 2005-2055 | H8: 2005-2055 | I8: 2010-2055 | J8: 2015 | K8: 2020 | L8: 2025-2055 | M8: 2010 | N8: 2015 | O8: 2020 | P8: 2025-2055 | Q8: 2015 | R8: 2020 | S8: 2025-2055 | T8: 2005 | U8: 2010 | V8: 2015 | W8: 2020 | X8: 2025-2055 | Y8: 2025 | Z8: 2030 | AA8: 2035
A9: R2,R3,R4,R5,R6,R7,R8,R9 | B9: ETH_CRN_H | C9: Total corn-based ethanol - historic | D9: uconstraint | E9: XCRNETH | F9: 1
A10: _GLOBAL | B10: ETH_CRN_H | C10: Total corn-based ethanol - historic | D10: uconstraint | E10: XCRNETH | M10: ='RFS2 Volumes'!$L$32 -> 1187.6224
A11: R2,R3,R4,R5,R6,R7,R8,R9 | B11: ETH_CRN | C11: Total corn-based ethanol | D11: uconstraint | E11: XCRNETH | F11: 1
A12: _GLOBAL | B12: ETH_CRN | C12: Total corn-based ethanol | D12: uconstraint | E12: XCRNETH | N12: =IF([2]Scenarios!$B$7="CAP",[2]Scenarios!I10,"") | O12: =IF([2]Scenarios!$B$7="CAP",[2]Scenarios!J10,"") | P12: =IF([2]Scenarios!$B$7="CAP",[2]Scenarios!K10,"") | Q12: =IF(Scenarios!$B$8="RFS",Scenarios!I8,IF(Scenarios!$B$8="20%U",Scenarios!I9,IF(Scenarios!$B$8="20%D",Scenarios!I10,0))) -> 1346.4337 | R12: =IF(Scenarios!$B$8="RFS",Scenarios!J8,IF(Scenarios!$B$8="20%U",Scenarios!J9,IF(Scenarios!$B$8="20%D",Scenarios!J10,0))) -> 1346.4337 | S12: =IF(Scenarios!$B$8="RFS",Scenarios!K8,IF(Scenarios!$B$8="20%U",Scenarios!K9,IF(Scenarios!$B$8="20%D",Scenarios!K10,0))) -> 1346.4337
A14: R1,R2,R3,R4,R5,R6,R7,R8,R9 | B14: BDL_TOT | C14: Total biodiesel | D14: uconstraint | E14: SCTRBDL | F14: 1
A15: _GLOBAL | B15: BDL_TOT | C15: Total biodiesel | D15: uconstraint | E15: SCTRBDL | M15: ='RFS2 Volumes'!L34 -> 42.151174 | V15: ='RFS2 Volumes'!$Q$41 -> 135.5958 | W15: ='RFS2 Volumes'!$V$41 -> 135.5958 | X15: ='RFS2 Volumes'!$X$41 -> 135.5958
A17: R1,R2,R3,R4,R5,R6,R7,R8,R9 | B17: ETH_IMPORT | C17: Total ethanol imported | D17: uconstraint | E17: ETH_IMP | G17: 1
A18: _GLOBAL | B18: ETH_IMPORT | C18: Total ethanol imported | D18: uconstraint | E18: ETH_IMP | M18: ='Int''l Exp+Imp'!F45 -> 15.985305 | N18: ='Int''l Exp+Imp'!G45 -> 101.4393 | O18: ='Int''l Exp+Imp'!H45 -> 269.28673 | P18: ='Int''l Exp+Imp'!I45 -> 314.16785
A19: R1,R2,R3,R4,R5,R6,R7,R8,R9 | B19: ETH_EXPORT | C19: Total ethanol exported | D19: uconstraint | E19: XETHEXP | F19: 1
A20: _GLOBAL | B20: ETH_EXPORT | C20: Total ethanol exported | D20: uconstraint | E20: XETHEXP | M20: ='Int''l Exp+Imp'!F47 -> 25.313215 | N20: ='Int''l Exp+Imp'!G47 -> 13.341267 | O20: ='Int''l Exp+Imp'!H47 -> 14.483977 | P20: ='Int''l Exp+Imp'!I47 -> 14.376036
A22: R1,R2,R3,R4,R5,R6,R7,R8,R9 | B22: BDL_IMPORT | C22: Total biodiesel imported | D22: uconstraint | E22: BDL_IMP | G22: 1
A23: _GLOBAL | B23: BDL_IMPORT | C23: Total biodiesel imported | D23: uconstraint | E23: BDL_IMP | M23: ='Int''l Exp+Imp'!F51 -> 0 | N23: ='Int''l Exp+Imp'!G51 -> 11.744785 | O23: ='Int''l Exp+Imp'!H51 -> 3.9459885 | P23: ='Int''l Exp+Imp'!I51 -> 0
A24: R1,R2,R3,R4,R5,R6,R7,R8,R9 | B24: BDL_EXPORT | C24: Total biodiesel exported | D24: uconstraint | E24: XBDLEXP | F24: 1
A25: _GLOBAL | B25: BDL_EXPORT | C25: Total biodiesel exported | D25: uconstraint | E25: XBDLEXP | M25: ='Int''l Exp+Imp'!F53 -> 9.4642116 | N25: ='Int''l Exp+Imp'!G53 -> 0 | O25: ='Int''l Exp+Imp'!H53 -> 0 | P25: ='Int''l Exp+Imp'!I53 -> 1.503658
A27: R1,R2,R3,R4,R5,R6,R7,R8,R9 | B27: BIOFL_ADV | C27: Total advanced biofuels | D27: uconstraint | E27: BIOF_ADV2 | G27: =IF([2]Scenarios!$B$18="Y",1,"") | H27: 1
A28: _GLOBAL | B28: BIOFL_ADV | C28: Total advanced biofuels | D28: uconstraint | E28: BIOF_ADV2 | J28: ='RFS2 Volumes'!$Q$40 -> 269.28673 | M28: ='RFS2 Volumes'!$L$40 -> 0 | Q28: =IF(Scenarios!$B$14="RFS",Scenarios!I14,IF(Scenarios!$B$14="20%U",Scenarios!I15,IF(Scenarios!$B$14="20%D",Scenarios!I16,0))) -> 0 | R28: =IF(Scenarios!$B$14="RFS",Scenarios!J14,IF(Scenarios!$B$14="20%U",Scenarios!J15,IF(Scenarios!$B$14="20%D",Scenarios!J16,0))) -> 0 | S28: =IF(Scenarios!$B$14="RFS",Scenarios!K14,IF(Scenarios!$B$14="20%U",Scenarios!K15,IF(Scenarios!$B$14="20%D",Scenarios!K16,0))) -> 0 | V28: ='RFS2 Volumes'!$Q$40 -> 269.28673 | W28: ='RFS2 Volumes'!$V$40 -> 942.50356 | X28: ='RFS2 Volumes'!$X$40 -> 1436.1959
A30: R1,R2,R3,R4,R5,R6,R7,R8,R9 | B30: E85_TOT | C30: Total E85 consumption | D30: uconstraint | E30: XBLNDE85 | F30: 1 | V30: ='RFS2 Volumes'!$C$47 -> 9.0650412 | W30: ='RFS2 Volumes'!$D$47 -> 277.85111 | Y30: ='RFS2 Volumes'!$E$47 -> 423.12915 | Z30: ='RFS2 Volumes'!$F$47 -> 948.44681 | AA30: ='RFS2 Volumes'!$G$47 -> 1383.4232
A31: _GLOBAL | B31: E85_TOT | C31: Total E85 consumption | D31: uconstraint | E31: XBLNDE85 | M31: ='Alt Fuel Vols'!F33 -> 12.054576 | N31: =M31*2 -> 24.109151

Sheet RFS2 Volumes
A1: ** Worksheet copied over from the BIOFUELS workbook
A2: Biofuels Volumes for Analysis
A4: EIA, Annual Energy Review | B4: EIA Annual Energy Review 2010, Table 10.3 and 10.4 | O4: Net imports of ethanol
B5: http://205.254.135.24/totalenergy/data/annual/#renewable | O5: 2000 | P5: 2001 | Q5: 2002 | R5: 2003 | S5: 2004 | T5: 2005 | U5: 2006 | V5: 2007 | W5: 2008 | X5: 2009 | Y5: 2010
N6: thous bbl | O6: 116 | P6: 315 | Q6: 306 | R6: 292 | S6: 3542 | T6: 3234 | U6: 17408 | V6: 10457 | W6: 12610 | X6: 4720 | Y6: 243
N7: gallons | O7: 4872000 | P7: 13230000 | Q7: 12852000 | R7: 12264000 | S7: 148764000 | T7: 135828000 | U7: 731136000 | V7: 439194000 | W7: 529620000 | X7: 198240000 | Y7: 10206000
N8: B gal | O8: 0.004872 | P8: 0.01323 | Q8: 0.012852 | R8: 0.012264 | S8: 0.148764 | T8: 0.135828 | U8: 0.731136 | V8: 0.439194 | W8: 0.52962 | X8: 0.19824 | Y8: 0.010206
A9: Volumes (Bgal)
B10: 2000 | C10: 2001 | D10: 2002 | E10: 2003 | F10: 2004 | G10: 2005 | H10: 2006 | I10: 2007 | J10: 2008 | K10: 2009 | L10: 2010 | O10: Biodiesel production
A11: Corn Ethanol | B11: 1.622334 | C11: 1.765176 | D11: 2.140152 | E11: 2.804424 | F11: 3.404436 | G11: 3.904362 | H11: 4.884348 | I11: 6.521046 | J11: 9.308754 | K11: 10.937808 | L11: 13.230756 | O11: 2000 | P11: 2001 | Q11: 2002 | R11: 2003 | S11: 2004 | T11: 2005 | U11: 2006 | V11: 2007 | W11: 2008 | X11: 2009 | Y11: 2010
A12: Net Imported Ethanol | B12: 0.004872 | C12: 0.01323 | D12: 0.012852 | E12: 0.012264 | F12: 0.148764 | G12: 0.135828 | H12: 0.731136 | I12: 0.439194 | J12: 0.52962 | K12: 0.19824 | L12: 0.010206 | N12: thous gal | P12: 8577 | Q12: 10484 | R12: 14210 | S12: 27982 | T12: 90787 | U12: 250439 | V12: 489825 | W12: 678106 | X12: 506275 | Y12: 310859
A13: Biodiesel | C13: 0.008577 | D13: 0.010484 | E13: 0.01421 | F13: 0.027982 | G13: 0.090787 | H13: 0.250439 | I13: 0.489825 | J13: 0.678106 | K13: 0.506275 | L13: 0.310859 | N13: B gal | P13: 0.008577 | Q13: 0.010484 | R13: 0.01421 | S13: 0.027982 | T13: 0.090787 | U13: 0.250439 | V13: 0.489825 | W13: 0.678106 | X13: 0.506275 | Y13: 0.310859
A15: EPA, RFS2 | B15: EPA Office of Transportation and Air Quality. "Regulatory Announcement: EPA Finalizes Regulations for the National Renewable Fuel Standard Program for 2010 and Beyond" EPA-420-F-10-007. February 2010. http://www.epa.gov/otaq/renewablefuels/420f10007.p
A17: Volumes (Bgal) | B17: 2000 | C17: 2001 | D17: 2002 | E17: 2003 | F17: 2004 | G17: 2005 | H17: 2006 | I17: 2007 | J17: 2008 | K17: 2009 | L17: 2010 | M17: 2011 | N17: 2012 | O17: 2013 | P17: 2014 | Q17: 2015 | R17: 2016 | S17: 2017 | T17: 2018 | U17: 2019 | V17: 2020 | W17: 2021 | X17: 2022
A18: Total Renewable Fuel Requirement | J18: 9 | K18: 11.1 | L18: 12.95 | M18: 13.95 | N18: 15.2 | O18: 16.55 | P18: 18.15 | Q18: 20.5 | R18: 22.25 | S18: 24 | T18: 26 | U18: 28 | V18: 30 | W18: 33 | X18: 36
A19: Total Advanced Biofuel Requirement | K19: 0.6 | L19: 0.95 | M19: 1.35 | N19: 2 | O19: 2.75 | P19: 3.75 | Q19: 5.5 | R19: 7.25 | S19: 9 | T19: 11 | U19: 13 | V19: 15 | W19: 18 | X19: 21
A20: Cellulosic Biofuel Requirement | L20: 0 | M20: 0.0065 | N20: 0.5 | O20: 1 | P20: 1.75 | Q20: 3 | R20: 4.25 | S20: 5.5 | T20: 7 | U20: 8.5 | V20: 10.5 | W20: 13.5 | X20: 16
A21: Biomass-based Diesel Requirement | K21: 0.5 | L21: 0.65 | M21: 0.8 | N21: 1 | O21: 1 | P21: 1 | Q21: 1 | R21: 1 | S21: 1 | T21: 1 | U21: 1 | V21: 1 | W21: 1 | X21: 1
A22: Other Advanced Biofuels | K22: 0.1 | L22: 0.3 | M22: 0.5435 | N22: 0.5 | O22: 0.75 | P22: 1 | Q22: 1.5 | R22: 2 | S22: 2.5 | T22: 3 | U22: 3.5 | V22: 3.5 | W22: 3.5 | X22: 4
A23: Difference (implied Corn Based Ethanol) | J23: 9 | K23: 10.5 | L23: 12 | M23: 12.6 | N23: 13.2 | O23: 13.8 | P23: 14.4 | Q23: 15 | R23: 15 | S23: 15 | T23: 15 | U23: 15 | V23: 15 | W23: 15 | X23: 15
C25: Based on market determination by EPA Administrator for setting the cellulosic standard each year
C26: To be determined through a future rulemaking (but no less than 1.0 billion gallons for biomass-based diesel)
A28: Conversion to PJ for MARKAL global constraints
A30: EIA, Annual Energy Review
A31: PJ | B31: 2000 | C31: 2001 | D31: 2002 | E31: 2003 | F31: 2004 | G31: 2005 | H31: 2006 | I31: 2007 | J31: 2008 | K31: 2009 | L31: 2010
A32: Corn Ethanol | B32: 145.62434 | C32: 158.44616 | D32: 192.10485 | E32: 251.73139 | F32: 305.58982 | G32: 350.4643 | H32: 438.43004 | I32: 585.34372 | J32: 835.57465 | K32: 981.80219 | L32: 1187.6224
A33: Net Imported Ethanol | B33: 0.43732165 | C33: 1.1875545 | D33: 1.1536244 | E33: 1.1008442 | F33: 13.353391 | G33: 12.192226 | H33: 65.628408 | I33: 39.423039 | J33: 47.53988 | K33: 17.794467 | L33: 0.91611347
A34: Biodiesel | B34: 0 | C34: 1.1630052 | D34: 1.4215863 | E34: 1.9268163 | F34: 3.7942416 | G34: 12.310336 | H34: 33.958476 | I34: 66.418211 | J34: 91.948324 | K34: 68.648762 | L34: 42.151174
A36: EPA, RFS2
A37: PJ | B37: 2000 | C37: 2001 | D37: 2002 | E37: 2003 | F37: 2004 | G37: 2005 | H37: 2006 | I37: 2007 | J37: 2008 | K37: 2009 | L37: 2010 | M37: 2011 | N37: 2012 | O37: 2013 | P37: 2014 | Q37: 2015 | R37: 2016 | S37: 2017 | T37: 2018 | U37: 2019 | V37: 2020 | W37: 2021 | X37: 2022
A38: Total Renewable Fuel Requirement | J38: 807.8602 | K38: 996.36091 | L38: 1162.4211 | M38: 1252.1833 | N38: 1364.3861 | O38: 1485.5651 | P38: 1629.1847 | Q38: 1840.126 | R38: 1997.2099 | S38: 2154.2939 | T38: 2333.8184 | U38: 2513.3428 | V38: 2692.8673 | W38: 2962.1541 | X38: 3231.4408
A39: Total Advanced Biofuel Requirement
A40: Cellulosic Biofuel | L40: 0 | M40: 0.58345459 | N40: 44.881122 | O40: 89.762244 | P40: 157.08393 | Q40: 269.28673 | R40: 381.48954 | S40: 493.69234 | T40: 628.33571 | U40: 762.97908 | V40: 942.50356 | W40: 1211.7903 | X40: 1436.1959
A41: Biomass-based Diesel | K41: 67.797899 | L41: 88.137268 | M41: 108.47664 | N41: 135.5958 | O41: 135.5958 | P41: 135.5958 | Q41: 135.5958 | R41: 135.5958 | S41: 135.5958 | T41: 135.5958 | U41: 135.5958 | V41: 135.5958 | W41: 135.5958 | X41: 135.5958
A42: Other Advanced Biofuels | K42: 8.9762244 | L42: 26.928673 | M42: 48.78578 | N42: 44.881122 | O42: 67.321683 | P42: 89.762244 | Q42: 134.64337 | R42: 179.52449 | S42: 224.40561 | T42: 269.28673 | U42: 314.16785 | V42: 314.16785 | W42: 314.16785 | X42: 359.04898
A43: Difference (implied Corn Based Ethanol) | J43: 807.8602 | K43: 942.50356 | L43: 1077.1469 | M43: 1131.0043 | N43: 1184.8616 | O43: 1238.719 | P43: 1292.5763 | Q43: 1346.4337 | R43: 1346.4337 | S43: 1346.4337 | T43: 1346.4337 | U43: 1346.4337 | V43: 1346.4337 | W43: 1346.4337 | X43: 1346.4337
A46: AEO 2012 | B46: 2010 | C46: 2015 | D46: 2020 | E46: 2025 | F46: 2030 | G46: 2035
A47: E85 consumption (PJ) | B47: 3.2105354 | C47: 9.0650412 | D47: 277.85111 | E47: 423.12915 | F47: 948.44681 | G47: 1383.4232
A48: Average annual growth rate by period | C48: 0.23071775 | D48: 0.98284365 | E48: 0.087757693 | F48: 0.17518978 | G48: 0.078421193

Sheet Scenarios
A1: ** Worksheet copied over from the BIOFUELS workbook
A2: Levers to represent 4 Future Scenarios for Air Quality
A4: Biofuels
C5: Bold | D5: setting for baseline
I7: 2015 | J7: 2020 | K7: 2025-55
A8: Corn based ethanol | B8: RFS | C8: RFS | D8: Meets RFS standard as lower bound | I8: 1346.4337 | J8: 1346.4337 | K8: 1346.4337
C9: 20%U | D9: Exceeeds RFS standard by 20% by 2015 as lower bound | I9: 1615.7204 | J9: 1615.7204 | K9: 1615.7204
C10: 20%D | D10: Below RFS standard by 20% by 2015 as lower bound | I10: 1077.1469 | J10: 1077.1469 | K10: 1077.1469
C11: CAP | D11: RFS as fixed bound | I11: 1346.4337 | J11: 1346.4337 | K11: 1346.4337
I13: 2015 | J13: 2020 | K13: 2025-55
A14: Advanced biofuels | B14: N | C14: RFS | D14: Meets RFS standard and stays | I14: 269.28673 | J14: 942.50356 | K14: 1436.1959
A15: All lower bounds | C15: 20%U | D15: Exceeeds RFS standard by 20% by 2025 | J15: 1131.0043 | K15: 1723.4351
C16: 20%D | D16: Below RFS standard by 20% by 2025 | J16: 754.00285 | K16: 1148.9567
C17: N | D17: No min advanced biofuel constraint | I17: 0 | J17: 0 | K17: 0
A19: Constraint on activity, not capacity | B19: N | C19: N | D19: Contraints for BIOF_ADV2 are based on capacity (as in base)
C20: Y | D20: Contraints for BIOF_ADV2 are based on activity
A22: Growth of advanced biofuels | B22: H | C22: H | D22: Growth constraints for adv biofuel techs, High = 1.8
C23: L | D23: Growth constraints for adv biofuel techs, Low = 1.2
A25: Limited E85 distribution | B25: Y | C25: Y | D25: Max 25% ratio of E85 to E10/gasoline blend in each region
C26: N | D26: Removes constraint, can maximize E85 blending in each region
A31: EPA, RFS2
A32: PJ | B32: 2015 | C32: 2020 | D32: 2022
A33: Total Renewable Fuel Requirement | B33: 1840.126 | C33: 2692.8673 | D33: 3231.4408
A34: Total Advanced Biofuel Requirement
A35: Cellulosic Biofuel | B35: 269.28673 | C35: 942.50356 | D35: 1436.1959
A36: Biomass-based Diesel | B36: 135.5958 | C36: 135.5958 | D36: 135.5958
A37: Other Advanced Biofuels | B37: 134.64337 | C37: 314.16785 | D37: 359.04898
A38: Difference (implied Corn Based Ethanol) | B38: 1346.4337 | C38: 1346.4337 | D38: 1346.4337

Sheet Int'l Exp+Imp
A1: ** Worksheet copied over from the BIOFUELS workbook
A2: Exports and Imports of Biofuels
A3: * The upper bounds on ethanol imports and biodiesel exports can also be linked to the projections for the RFS2 RIA.
B5: CARD Variable | C5: Units
A7: Ethanol imports | D7: 2000 | E7: 2005 | F7: 2010 | G7: 2015 | H7: 2020 | I7: 2025 | J7: 2030-2050
A8: Ethyl alcohol net imports, cal. yr. | B8: ETSIMNCL | C8: million gallons | D8: 111.10066 | E8: 149.80449 | F8: -224 | G8: 981.45975 | H8: 2838.6407 | I8: 3339.8432 | J8: 3339.8432
A9: Anhydrous ethanol price, Brazil | B9: ETPBZAMA | C9: dollars per gallon | D9: 1.2324594 | E9: 1.5566491 | F9: 1.9949182 | G9: 2.2232995 | H9: 2.6365053 | I9: 2.4835173 | J9: 2.4835173
A10: Ethanol ad valorem tariff, cal. yr. | B10: ETTARV | C10: percent | D10: 0.025 | E10: 0.025 | F10: 0.025 | G10: 0 | H10: 0 | I10: 0 | J10: 0
A11: Ethanol specific tariff, cal. yr. | B11: ETTARS | C11: dollars per gallon | D11: 0.54 | E11: 0.54 | F11: 0.54 | G11: 0 | H11: 0 | I11: 0 | J11: 0
C13: MY | D13: 1999 | E13: 2000 | F13: 2004 | G13: 2005 | H13: 2009 | I13: 2010 | J13: 2014 | K13: 2015 | L13: 2019 | M13: 2020 | N13: 2024 | O13: 2025 | P13: << for converting from marketing year to calendar year
A14: Ethyl alcohol imports (gal, S-A) | B14: ETSIMPSA | C14: million gallons | D14: 171.25518 | E14: 146.66153 | F14: 153.99309 | G14: 551.75669 | H14: 175.37991 | I14: 183.49506 | J14: 1028.4664 | K14: 1333.3333 | L14: 3000 | M14: 3000 | N14: 3500 | O14: 3500 | R14: CY1 = (2/3)*MY0 + (1/3)*MY1
A15: Ethyl alcohol exports (gal, S-A) | B15: ETDEXPSA | C15: million gallons | D15: 41.299192 | E15: 83.251464 | F15: 56.950943 | G15: 49.492423 | H15: 262.76079 | I15: 320.48718 | J15: 147.73671 | K15: 150.41339 | L15: 161.4055 | M15: 161.26703 | N15: 160.17554 | O15: 160.1194
C16: Check net imports | D16: 129.95598 | E16: 63.410069 | F16: 97.042148 | G16: 502.26426 | H16: -87.380882 | I16: -136.99212 | J16: 880.72966 | K16: 1182.9199 | L16: 2838.5945 | M16: 2838.733 | N16: 3339.8245 | O16: 3339.8806
C18: CY | D18: 2000 | E18: 2005 | F18: 2010 | G18: 2015 | H18: 2020 | I18: 2025 | J18: 2030-2050
A19: Ethyl alcohol imports (CY) | C19: million gallons | D19: 163.05729 | E19: 286.58096 | F19: 178.08496 | G19: 1130.0887 | H19: 3000 | I19: 3500 | J19: 3500
A20: Ethyl alcohol exports (CY) | C20: million gallons | D20: 55.283282 | E20: 54.46477 | F20: 282.00292 | G20: 148.62894 | H20: 161.35935 | I20: 160.15683 | J20: 160.15683
C21: Check net imports | D21: 107.77401 | E21: 232.11619 | F21: -103.91796 | G21: 981.45975 | H21: 2838.6407 | I21: 3339.8432 | J21: 3339.8432
A23: Biodiesel Exports | C23: MY | D23: 1999 | E23: 2000 | F23: 2004 | G23: 2005 | H23: 2009 | I23: 2010 | J23: 2014 | K23: 2015 | L23: 2019 | M23: 2020 | N23: 2024 | O23: 2025 | P23: << for converting from marketing year to calendar year
A24: Biodiesel net exports, MY | B24: BDDEXN | C24: million gallons | D24: 0 | E24: 0 | F24: 0 | G24: 0.3454276 | H24: 129.57 | I24: -49.748298 | J24: -90.216675 | K24: -79.41508 | L24: -32.085784 | M24: -23.131767 | N24: 7.9573514 | O24: 17.353097
A25: Biodiesel price, Germany, MY | B25: BDPGER | C25: dollars per gallon | D25: 0 | E25: 0 | F25: 3.1248367 | G25: 3.3004946 | H25: 4.1477168 | I25: 4.6304786 | J25: 4.983183 | K25: 5.0630787 | L25: 5.4794407 | M25: 5.5793843 | N25: 5.9492109 | O25: 6.0285564
C27: CY | D27: 2000 | E27: 2005 | F27: 2010 | G27: 2015 | H27: 2020 | I27: 2025 | J27: 2030-2050
A28: Biodiesel net exports, CY | C28: million gallons | D28: 0 | E28: 0.11514253 | F28: 69.797234 | G28: -86.616143 | H28: -29.101112 | I28: 11.089267 | J28: 11.089267
A29: Biodiesel price, Germany, CY | C29: dollars per gallon | D29: 0 | E29: 3.1833893 | F29: 4.3086374 | G29: 5.0098149 | H29: 5.5127552 | I29: 5.9756594 | J29: 5.9756594
A31: Biodiesel imports, CY | B31: XXXX | C31: million gallons | G31: 86.616143 | H31: 29.101112
C32: dollars per gallon | D32: 0 | E32: 3.1833893 | F32: 4.3086374 | G32: 5.0098149 | H32: 5.5127552 | I32: 5.9756594 | J32: 5.9756594
A33: Biodiesel exports, CY | B33: XXXX | C33: million gallons | D33: 0 | E33: 0.11514253 | F33: 69.797234 | I33: 11.089267 | J33: 11.089267
C34: dollars per gallon | D34: 0 | E34: 3.1833893 | F34: 4.3086374 | G34: 5.0098149 | H34: 5.5127552 | I34: 5.9756594 | J34: 5.9756594
B38: MARKAL Parameter | C38: Units
A39: Price of imported (Brazilian) ethanol with ad valorem | C39: M$/PJ | D39: 14.073521 | E39: 17.775461 | F39: 22.78008 | G39: 24.76876 | H39: 29.372097 | I39: 27.667727 | J39: 27.667727
A40: Ethanol specific tariff applied | C40: M$/PJ | D40: 6.0158924 | E40: 6.0158924 | F40: 6.0158924 | G40: 0 | H40: 0 | I40: 0 | J40: 0
A41: Cost of imported ethanol (sum of above) | C41: M$/PJ | D41: 20.089413 | E41: 23.791354 | F41: 28.795973 | G41: 24.76876 | H41: 29.372097 | I41: 27.667727 | J41: 27.667727
A44: Cost of imported ethanol | C44: M$/PJ | D44: 20.089413 | E44: 23.791354 | F44: 28.795973 | G44: 24.76876 | H44: 29.372097 | I44: 27.667727 | J44: 27.667727
A45: Global constraint for imported ethanol | C45: PJ | D45: 14.636389 | E45: 25.72415 | F45: 15.985305 | G45: 101.4393 | H45: 269.28673 | I45: 314.16785 | J45: 314.16785
A46: Cost of exported ethanol | C46: M$/PJ | D46: 20.089413 | E46: 23.791354 | F46: 28.795973 | G46: 24.76876 | H46: 29.372097 | I46: 27.667727 | J46: 27.667727
A47: Global constraint for exported ethanol | C47: PJ | D47: 4.9623515 | E47: 4.88888 | F47: 25.313215 | G47: 13.341267 | H47: 14.483977 | I47: 14.376036 | J47: 14.376036
A50: Cost of imported biodiesel | C50: M$/PJ | D50: 0 | E50: 24.340685 | F50: 34.149131 | G50: 37.339496 | H50: 41.147177 | I50: 44.459759 | J50: 44.459759
A51: Global constraint for imported biodiesel | C51: PJ | D51: 0 | E51: 0 | F51: 0 | G51: 11.744785 | H51: 3.9459885 | I51: 0 | J51: 0
A52: Cost of exported biodiesel | C52: M$/PJ | D52: 0 | E52: 24.340685 | F52: 34.149131 | G52: 37.339496 | H52: 41.147177 | I52: 44.459759 | J52: 44.459759
A53: Global constraint for exported biodiesel | C53: PJ | D53: 0 | E53: 0.015612844 | F53: 9.4642116 | G53: 0 | H53: 0 | I53: 1.503658 | J53: 1.503658

Sheet Alt Fuel Vols
A1: ** Worksheet copied over from the BIOFUELS workbook
A2: Note: This table is included to calibrate historic levels of fuel consumption for biofuels, specifically, E85
A4: Estimated Consumption of Vehicle Fuels in Native Units, by Fuel Type, 2007 - 2011
A5: Fuel Type | B5: Units | C5: 2007 | D5: 2008 | E5: 2009 | F5: 2010 | G5: 2011
A6: Alternative Fuels
A7: Compressed Natural Gas | B7: million cubic feet | C7: 21514 | D7: 22814 | E7: 24038 | F7: 25302 | G7: 26536
A8: Electricity | B8: thousand kilowatt hours | C8: 167900 | D8: 168333 | E8: 165200 | F8: 161567 | G8: 254500
A9: Ethanol, 85 percent1 | B9: thousand gallons | C9: 75126 | D9: 86756 | E9: 98907 | F9: 125449 | G9: 190507
A10: Hydrogen | B10: thousand kilograms | C10: 60 | D10: 107 | E10: 128 | F10: 138 | G10: 158
A11: Liquefied Natural Gas | B11: thousand gallons | C11: 37264 | D11: 38718 | E11: 38867 | F11: 39503 | G11: 39761
A12: Liquefied Petroleum Gas | B12: thousand gallons | C12: 205892 | D12: 199708 | E12: 175177 | F12: 170749 | G12: 168185
A13: Other Fuels2 | C13: na | D13: na | E13: na | F13: 0 | G13: 0
A14: Replacement Fuels3
A15: Biodiesel | B15: thousand gallons | C15: 358156 | D15: 315796 | E15: 326,000[R] | F15: 263,000[R] | G15: 887000
A16: Ethanol in Gasohol | B16: thousand gallons | C16: 6885690 | D16: 9435428 | E16: 10753990 | F16: 12495404 | G16: 12548757
A17: Traditional Fuels Used On-Highway
A18: Gasoline4 | B18: thousand gallons | C18: 140646000 | D18: 134644492 | E18: 134385175 | F18: 134686678 | G18: 130597071
A19: Diesel4 | B19: thousand gallons | C19: 39373000 | D19: 37528464 | E19: 34147806 | F19: 35582625 | G19: 36160000
A21: 1The remaining portion of 85-percent ethanol is gasoline. Consumption data include the gasoline portion of the fuel.
A22: 2May include P-Series fuel or any other fuel designated by the Secretary of Energy as an alternative fuel under the Energy Policy Act of 1992.
A23: 3MTBE and Other Oxygenates are no longer published in this table. Highway use was assumed to be zero after 2006, since U.S. refineries and blenders voluntarily discontinued the use of MTBE in highway gasoline in mid-2006.
A24: 4Gasoline consumption includes ethanol in gasohol. Diesel includes biodiesel. Gasoline and diesel values are rounded to the nearest million gallons.
A25: Notes: R = Revised.
A26: Sources:
A27: Biodiesel: U.S. Energy Information Administration, Monthly Energy Review, January 2013, Table 10.4, Consumption.
A28: Ethanol: U.S. Energy Information Administration, Monthly Energy Review, January 2013 Table 10.3, Consumption. Highway use of ethanol estimated by applying the fraction of gasoline used on-highway for each year to the ethanol quantity.
A29: Gasoline: U.S. Energy Information Administration, Petroleum Supply Annual 2011 Volume 1, Table 1, Product Supplied. The fraction of gasoline used on-highway was determined from the Federal Highway Administration`s "Highway Statistics" for 2011. Highway use of gasoline and total use of gasoline are found in Table MF-21 for the applicable year. Aviation gasoline use is found in Table MF-24 for the applicable year. The fraction used for 2011 is 0.9733 and is calculated as (total highway use of gasoline)/(total use of gasoline - aviation gasoline).
A30: Diesel: U.S.Energy Information Administration, Fuel Oil and Kerosene Sales 2011, Table 1, Sales of Distillate Fuel Oil, On-Highway.
F32: 2010
E33: E85 (PJ) | F33: 12.054576
A35: http://www.eia.gov/renewable/afv/?src=Renewable-b4

Sheet ANSv6.0-ConstrData
A1: ANSWER-ConstrData
B7: ConstrName | C7: ConstrDesc | D7: Units | E7: TechName

Sheet ANSv6.0-TechData
A1: ANSWER-TechData
B7: TechName | C7: TechDesc | D7: Units | E7: CommIN | F7: CommOUT

Sheet ANSv6.0-CommData
A1: ANSWER-CommData
B7: CommName | C7: CommDesc | D7: Units

Sheet ANSv6.0-Constraints
A1: ANSWER-Constraints
B7: ConstrName | C7: ConstrDesc | D7: Units | E7: Set Memberships | F7: Comment
